datecycles/__init__.py
datecycles/datecycles.py
datecycles-0.1.2.dist-info/LICENSE
datecycles-0.1.2.dist-info/WHEEL
datecycles-0.1.2.dist-info/METADATA
datecycles-0.1.2.dist-info/RECORD
