Metadata-Version: 2.1
Name: datecycles
Version: 0.1.2
Summary: Simple library for complicated date cycling rules
Home-page: https://github.com/b10011/datecycles
License: MIT
Keywords: date,time,calendar,cycling
Author: Niko Järvinen
Author-email: nbjarvinen@gmail.com
Requires-Python: >=3.6,<4.0
Classifier: Development Status :: 4 - Beta
Classifier: Intended Audience :: Developers
Classifier: License :: OSI Approved :: MIT License
Classifier: Programming Language :: Python :: 3
Classifier: Programming Language :: Python :: 3.6
Classifier: Programming Language :: Python :: 3.7
Classifier: Programming Language :: Python :: 3.8
Classifier: Programming Language :: Python :: 3.9
Classifier: Topic :: Software Development :: Libraries
Classifier: Topic :: Utilities
Requires-Dist: arrow (>=1.1.1,<2.0.0)
Requires-Dist: holidays (>=0.11.1,<0.12.0)
Project-URL: Documentation, https://github.com/b10011/datecycles
Project-URL: Repository, https://github.com/b10011/datecycles
